highlighter/__init__.py
highlighter/__main__.py
highlighter/analyzer.py
highlighter/common.py
highlighter/processor.py
auto_highlighter_py-0.1.0.dist-info/METADATA
auto_highlighter_py-0.1.0.dist-info/WHEEL
auto_highlighter_py-0.1.0.dist-info/top_level.txt
auto_highlighter_py-0.1.0.dist-info/RECORD
