Metadata-Version: 2.1
Name: auto-highlighter-py
Version: 0.1.0
Summary: automatically clip moments from twitch VODs
Requires-Python: >=3.10
Requires-Dist: ffmpeg-python >=0.2.0
Requires-Dist: librosa >=0.10.2.post1
Requires-Dist: loguru >=0.7.2
Requires-Dist: numpy >=2.0.2
Requires-Dist: rich >=13.9.3
Requires-Dist: scikit-learn >=1.5.2
Requires-Dist: typer >=0.12.5
